expedatetimemint/main.py
expedatetimemint-20241023.post12019.dist-info/METADATA
expedatetimemint-20241023.post12019.dist-info/WHEEL
expedatetimemint-20241023.post12019.dist-info/entry_points.txt
expedatetimemint-20241023.post12019.dist-info/top_level.txt
expedatetimemint-20241023.post12019.dist-info/RECORD
