Metadata-Version: 2.1
Name: expedatetimemint
Version: 20241023.post12019
Summary: 🥭 A simple CLI tool to display the current date and time with a random fruit or vegetable emoji.
Author-email: "com.andrewalevin 🍋" <your_email@example.com>
License: MIT
Keywords: datetime,emoji,CLI
Classifier: Programming Language :: Python :: 3
Classifier: License :: OSI Approved :: MIT License
Classifier: Operating System :: OS Independent
Requires-Python: >=3.6
Provides-Extra: dev
Requires-Dist: pytest; extra == "dev"
Requires-Dist: flake8; extra == "dev"
